napari_ism/__init__.py
napari_ism/_reader.py
napari_ism/_sample_data.py
napari_ism/_widget.py
napari_ism/_writer.py
napari_ism/napari.yaml
napari_ISM-1.0.7.dist-info/LICENSE
napari_ISM-1.0.7.dist-info/METADATA
napari_ISM-1.0.7.dist-info/WHEEL
napari_ISM-1.0.7.dist-info/entry_points.txt
napari_ISM-1.0.7.dist-info/top_level.txt
napari_ISM-1.0.7.dist-info/RECORD
