Metadata-Version: 2.1
Name: napari-ISM
Version: 1.0.7
Summary: A Napari plugin for analysing and simulating ISM images
Home-page: https://github.com/VicidominiLab/napari-ISM
Author: Alessandro Zunino
Author-email: Alessandro Zunino <alessandro.zunino@iit.it>
Project-URL: Homepage, https://github.com/VicidominiLab/napari-ism
Project-URL: Documentation, https://brighteyes-ism.readthedocs.io
Classifier: Framework :: napari
Classifier: Programming Language :: Python :: 3.7
Classifier: Programming Language :: Python :: 3.8
Classifier: Programming Language :: Python :: 3.9
Classifier: Programming Language :: Python :: 3.10
Classifier: Operating System :: OS Independent
Classifier: License :: OSI Approved :: GNU General Public License v3 or later (GPLv3+)
Requires-Python: >=3.7
License-File: LICENSE
Requires-Dist: numpy
Requires-Dist: scipy
Requires-Dist: h5py
Requires-Dist: PyQt5
Requires-Dist: brighteyes-ism >=1.2.2
Provides-Extra: testing
Requires-Dist: tox ; extra == 'testing'
Requires-Dist: pytest ; extra == 'testing'
Requires-Dist: pytest-cov ; extra == 'testing'
Requires-Dist: pytest-qt ; extra == 'testing'
Requires-Dist: napari ; extra == 'testing'
Requires-Dist: pyqt5 ; extra == 'testing'
